package_danu/__init__.py
package_danu/guess_number.py
package_danu/weight_conversion.py
package_danu-0.1.0.dist-info/METADATA
package_danu-0.1.0.dist-info/WHEEL
package_danu-0.1.0.dist-info/top_level.txt
package_danu-0.1.0.dist-info/RECORD
